{"temperatures":[ {"time": 1776783664294, "temp": 15.0, "bat": 3}, {"time": 1776784264556, "temp": 15.1, "bat": 3}, {"time": 1776784864397, "temp": 15.1, "bat": 3}, {"time": 1776785465194, "temp": 14.6, "bat": 3}, {"time": 1776786069355, "temp": 14.0, "bat": 3}, {"time": 1776786665034, "temp": 14.8, "bat": 3}, {"time": 1776787265477, "temp": 14.8, "bat": 3}, {"time": 1776787865428, "temp": 14.8, "bat": 3}, {"time": 1776788466393, "temp": 14.8, "bat": 3}, {"time": 1776789071436, "temp": 14.6, "bat": 3}, {"time": 1776789666477, "temp": 14.5, "bat": 3}, {"time": 1776790266990, "temp": 14.6, "bat": 3}, {"time": 1776791427523, "temp": 14.7, "bat": 3}, {"time": 1776792027453, "temp": 14.8, "bat": 3}, {"time": 1776792627420, "temp": 15.1, "bat": 3}, {"time": 1776793228245, "temp": 14.8, "bat": 3}, {"time": 1776793832307, "temp": 14.8, "bat": 3}, {"time": 1776794428470, "temp": 14.3, "bat": 3}, {"time": 1776795027514, "temp": 13.9, "bat": 3}, {"time": 1776795627668, "temp": 13.7, "bat": 3}, {"time": 1776796228462, "temp": 13.4, "bat": 3}, {"time": 1776796833505, "temp": 13.3, "bat": 3}, {"time": 1776797428461, "temp": 12.9, "bat": 3}, {"time": 1776798028567, "temp": 12.6, "bat": 3}, {"time": 1776798629829, "temp": 11.9, "bat": 3}, {"time": 1776799229517, "temp": 11.9, "bat": 3}, {"time": 1776799834542, "temp": 11.6, "bat": 3}, {"time": 1776800429517, "temp": 11.5, "bat": 3}, {"time": 1776801029608, "temp": 10.6, "bat": 3}, {"time": 1776801629591, "temp": 11.4, "bat": 3}, {"time": 1776802229613, "temp": 11.1, "bat": 3}, {"time": 1776802834630, "temp": 11.2, "bat": 3}, {"time": 1776803429676, "temp": 11.1, "bat": 3}, {"time": 1776804029743, "temp": 11.1, "bat": 3}, {"time": 1776804629742, "temp": 10.8, "bat": 3}, {"time": 1776805230781, "temp": 10.8, "bat": 3}, {"time": 1776805836713, "temp": 10.3, "bat": 3}, {"time": 1776807632151, "temp": 11.3, "bat": 3}, {"time": 1776808237194, "temp": 11.4, "bat": 3}, {"time": 1776808832710, "temp": 12.4, "bat": 3}, {"time": 1776809432190, "temp": 13.2, "bat": 3}, {"time": 1776810032234, "temp": 13.7, "bat": 3}, {"time": 1776810632380, "temp": 13.5, "bat": 3}, {"time": 1776811237187, "temp": 15.4, "bat": 3}, {"time": 1776815432378, "temp": 21.3, "bat": 3}, {"time": 1776816032378, "temp": 21.6, "bat": 3}, {"time": 1776816637372, "temp": 21.9, "bat": 3}, {"time": 1776817232294, "temp": 23.4, "bat": 3}, {"time": 1776817832306, "temp": 25.6, "bat": 3}, {"time": 1776818432302, "temp": 28.2, "bat": 3}, {"time": 1776819032427, "temp": 28.2, "bat": 3}, {"time": 1776819637349, "temp": 27.3, "bat": 3}, {"time": 1776820232383, "temp": 26.5, "bat": 3}, {"time": 1776820832470, "temp": 25.7, "bat": 3}, {"time": 1776821432465, "temp": 26.3, "bat": 3}, {"time": 1776822032614, "temp": 26.8, "bat": 3}, {"time": 1776822637513, "temp": 26.3, "bat": 3}, {"time": 1776823232463, "temp": 26.8, "bat": 3}, {"time": 1776823832603, "temp": 27.2, "bat": 3}, {"time": 1776824432747, "temp": 28.8, "bat": 3}, {"time": 1776825032552, "temp": 28.4, "bat": 3}, {"time": 1776825637868, "temp": 27.8, "bat": 3}, {"time": 1776826237590, "temp": 27.3, "bat": 3}, {"time": 1776826832645, "temp": 26.1, "bat": 3}, {"time": 1776827432704, "temp": 25.6, "bat": 3}, {"time": 1776828032714, "temp": 25.0, "bat": 3}, {"time": 1776828638148, "temp": 24.0, "bat": 3}, {"time": 1776829233090, "temp": 23.6, "bat": 3}, {"time": 1776829833028, "temp": 22.6, "bat": 3}, {"time": 1776830432725, "temp": 22.5, "bat": 3}, {"time": 1776831032992, "temp": 22.2, "bat": 3}, {"time": 1776831639113, "temp": 21.4, "bat": 3}, {"time": 1776832233742, "temp": 21.4, "bat": 3}, {"time": 1776832835263, "temp": 21.3, "bat": 3}, {"time": 1776833434787, "temp": 21.4, "bat": 3}, {"time": 1776834035829, "temp": 21.7, "bat": 3}, {"time": 1776834642803, "temp": 21.7, "bat": 3}, {"time": 1776835238495, "temp": 21.6, "bat": 3}, {"time": 1776835837930, "temp": 19.6, "bat": 3}, {"time": 1776836437952, "temp": 20.2, "bat": 3}, {"time": 1776837038140, "temp": 19.3, "bat": 3}, {"time": 1776837643984, "temp": 18.7, "bat": 3}, {"time": 1776838239508, "temp": 18.5, "bat": 3}, {"time": 1776838839905, "temp": 18.3, "bat": 3}, {"time": 1776839442625, "temp": 17.5, "bat": 3}, {"time": 1776840041987, "temp": 17.7, "bat": 3}, {"time": 1776841243602, "temp": 17.7, "bat": 3}, {"time": 1776841842299, "temp": 17.1, "bat": 3}, {"time": 1776842443761, "temp": 16.9, "bat": 3}, {"time": 1776843049041, "temp": 16.7, "bat": 3}, {"time": 1776843644879, "temp": 16.7, "bat": 3}, {"time": 1776844245929, "temp": 16.4, "bat": 3}, {"time": 1776844845345, "temp": 16.2, "bat": 3}, {"time": 1776845447109, "temp": 16.2, "bat": 3}, {"time": 1776846051355, "temp": 16.1, "bat": 3}, {"time": 1776846646463, "temp": 16.1, "bat": 3}, {"time": 1776847247419, "temp": 16.0, "bat": 3}, {"time": 1776847847507, "temp": 15.9, "bat": 3}, {"time": 1776848448061, "temp": 15.6, "bat": 3}, {"time": 1776849052553, "temp": 14.5, "bat": 3}, {"time": 1776849648072, "temp": 15.3, "bat": 3}, {"time": 1776850247508, "temp": 15.1, "bat": 3}, {"time": 1776850847511, "temp": 14.3, "bat": 3}, {"time": 1776851447590, "temp": 15.1, "bat": 3}, {"time": 1776852053187, "temp": 15.3, "bat": 3}, {"time": 1776852647590, "temp": 14.9, "bat": 3}, {"time": 1776853247581, "temp": 14.0, "bat": 3}, {"time": 1776853847664, "temp": 15.0, "bat": 3}, {"time": 1776854447515, "temp": 15.1, "bat": 3}, {"time": 1776855052938, "temp": 14.7, "bat": 3}, {"time": 1776855648058, "temp": 15.0, "bat": 3}, {"time": 1776856247807, "temp": 14.8, "bat": 3}, {"time": 1776856848060, "temp": 15.0, "bat": 3}, {"time": 1776857448402, "temp": 14.6, "bat": 3}, {"time": 1776858053291, "temp": 14.8, "bat": 3}, {"time": 1776858647588, "temp": 14.6, "bat": 3}, {"time": 1776859248617, "temp": 14.5, "bat": 3}, {"time": 1776859849108, "temp": 14.7, "bat": 3}, {"time": 1776860449346, "temp": 14.6, "bat": 3}, {"time": 1776861063855, "temp": 14.6, "bat": 3}, {"time": 1776861648714, "temp": 14.7, "bat": 3}, {"time": 1776862248717, "temp": 14.7, "bat": 3}, {"time": 1776862848701, "temp": 14.5, "bat": 3}, {"time": 1776863448794, "temp": 14.6, "bat": 3}, {"time": 1776864053743, "temp": 14.3, "bat": 3}, {"time": 1776864648794, "temp": 14.7, "bat": 3}, {"time": 1776865248788, "temp": 14.4, "bat": 3}, {"time": 1776865848873, "temp": 14.8, "bat": 3}, {"time": 1776866448859, "temp": 14.8, "bat": 3}, {"time": 1776867053908, "temp": 14.5, "bat": 3}, {"time": 1776867648860, "temp": 14.2, "bat": 3}, {"time": 1776868248864, "temp": 14.4, "bat": 3}, {"time": 1776868848795, "temp": 14.6, "bat": 3}, {"time": 1776869448865, "temp": 14.5, "bat": 3}, {"time": 1776870053984, "temp": 14.2, "bat": 3}, {"time": 1776870648902, "temp": 14.2, "bat": 3}, {"time": 1776871249340, "temp": 14.8, "bat": 3}, {"time": 1776871848942, "temp": 14.4, "bat": 3}, {"time": 1776872448942, "temp": 14.6, "bat": 3}, {"time": 1776873053976, "temp": 14.5, "bat": 3}, {"time": 1776873649027, "temp": 14.5, "bat": 3}, {"time": 1776874249024, "temp": 14.5, "bat": 3}, {"time": 1776874848945, "temp": 14.6, "bat": 3}, {"time": 1776875449022, "temp": 14.5, "bat": 3}, {"time": 1776876053978, "temp": 14.5, "bat": 3}, {"time": 1776876649025, "temp": 14.5, "bat": 3}, {"time": 1776877257342, "temp": 14.5, "bat": 3}, {"time": 1776877869024, "temp": 14.7, "bat": 3}, {"time": 1776878469023, "temp": 14.7, "bat": 3}, {"time": 1776879069103, "temp": 14.6, "bat": 3}, {"time": 1776879669114, "temp": 14.4, "bat": 3}, {"time": 1776880274156, "temp": 14.6, "bat": 3}, {"time": 1776880869836, "temp": 14.8, "bat": 3}, {"time": 1776881469229, "temp": 14.9, "bat": 3}, {"time": 1776882069106, "temp": 14.6, "bat": 3}, {"time": 1776882669108, "temp": 14.5, "bat": 3}, {"time": 1776883274158, "temp": 14.8, "bat": 3}, {"time": 1776883869187, "temp": 14.8, "bat": 3}, {"time": 1776884469271, "temp": 14.8, "bat": 3}, {"time": 1776885069265, "temp": 14.0, "bat": 3}, {"time": 1776885669357, "temp": 14.5, "bat": 3}, {"time": 1776886269262, "temp": 14.8, "bat": 3}, {"time": 1776886869757, "temp": 14.9, "bat": 3}, {"time": 1776887469352, "temp": 15.1, "bat": 3}, {"time": 1776888070304, "temp": 15.1, "bat": 3}, {"time": 1776888670389, "temp": 15.2, "bat": 3}, {"time": 1776889275350, "temp": 15.1, "bat": 3}, {"time": 1776889870312, "temp": 14.6, "bat": 3}, {"time": 1776890470298, "temp": 15.2, "bat": 3}, {"time": 1776891071343, "temp": 15.3, "bat": 3}, {"time": 1776891671184, "temp": 14.7, "bat": 3}, {"time": 1776892277265, "temp": 15.1, "bat": 3}, {"time": 1776892872301, "temp": 15.6, "bat": 3}, {"time": 1776893472299, "temp": 15.4, "bat": 3}, {"time": 1776894074301, "temp": 15.2, "bat": 3}, {"time": 1776894674296, "temp": 15.8, "bat": 3}, {"time": 1776895280061, "temp": 15.8, "bat": 3}, {"time": 1776895875263, "temp": 15.9, "bat": 3}, {"time": 1776896475348, "temp": 15.4, "bat": 3}, {"time": 1776897075344, "temp": 16.0, "bat": 3}, {"time": 1776897676856, "temp": 16.1, "bat": 3}, {"time": 1776898281260, "temp": 16.0, "bat": 3}, {"time": 1776898877345, "temp": 16.6, "bat": 3}, {"time": 1776899477472, "temp": 16.0, "bat": 3}, {"time": 1776900077506, "temp": 17.1, "bat": 3}, {"time": 1776900677265, "temp": 17.4, "bat": 3}, {"time": 1776901282311, "temp": 17.5, "bat": 3}, {"time": 1776901877820, "temp": 17.0, "bat": 3}, {"time": 1776902477500, "temp": 18.2, "bat": 3}, {"time": 1776903077920, "temp": 18.4, "bat": 3}, {"time": 1776903677507, "temp": 18.6, "bat": 3}, {"time": 1776904282387, "temp": 18.6, "bat": 3}, {"time": 1776904882391, "temp": 18.6, "bat": 3}, {"time": 1776905477425, "temp": 18.8, "bat": 3}, {"time": 1776906078473, "temp": 19.6, "bat": 3}, {"time": 1776906679102, "temp": 20.5, "bat": 3}, {"time": 1776907286786, "temp": 20.5, "bat": 3}, {"time": 1776907879430, "temp": 20.0, "bat": 3}, {"time": 1776908484462, "temp": 23.0, "bat": 3}, {"time": 1776909079506, "temp": 23.8, "bat": 3}, {"time": 1776909679736, "temp": 24.4, "bat": 3}, {"time": 1776910285508, "temp": 24.3, "bat": 3}, {"time": 1776910884013, "temp": 23.9, "bat": 3}, {"time": 1776911481510, "temp": 23.4, "bat": 3}, {"time": 1776912081998, "temp": 21.9, "bat": 3}, {"time": 1776912681508, "temp": 22.7, "bat": 3}, {"time": 1776913287192, "temp": 22.1, "bat": 3}, {"time": 1776913881663, "temp": 22.1, "bat": 3}, {"time": 1776914481512, "temp": 22.1, "bat": 3}, {"time": 1776915081499, "temp": 22.0, "bat": 3}, {"time": 1776915681531, "temp": 21.9, "bat": 3}, {"time": 1776916288805, "temp": 20.7, "bat": 3}, {"time": 1776916882629, "temp": 21.4, "bat": 3}, {"time": 1776917483123, "temp": 21.1, "bat": 3}, {"time": 1776918082542, "temp": 20.6, "bat": 3}, {"time": 1776918683588, "temp": 20.8, "bat": 3}, {"time": 1776919288561, "temp": 20.5, "bat": 3}, {"time": 1776919883587, "temp": 19.5, "bat": 3}, {"time": 1776920483666, "temp": 20.2, "bat": 3}, {"time": 1776921083581, "temp": 19.9, "bat": 3}, {"time": 1776921683672, "temp": 19.0, "bat": 3}, {"time": 1776922288628, "temp": 20.1, "bat": 3}, {"time": 1776922883746, "temp": 19.8, "bat": 3}, {"time": 1776923484634, "temp": 19.3, "bat": 3}, {"time": 1776924085739, "temp": 19.5, "bat": 3}, {"time": 1776924685662, "temp": 19.8, "bat": 3}, {"time": 1776925292223, "temp": 20.0, "bat": 3}, {"time": 1776925898314, "temp": 19.7, "bat": 3}, {"time": 1776926488395, "temp": 19.8, "bat": 3}, {"time": 1776927088798, "temp": 19.7, "bat": 3}, {"time": 1776927690298, "temp": 19.0, "bat": 3}, {"time": 1776928295105, "temp": 19.8, "bat": 3}, {"time": 1776928890784, "temp": 19.8, "bat": 3}, {"time": 1776929490777, "temp": 20.1, "bat": 3}, {"time": 1776930090947, "temp": 19.5, "bat": 3}, {"time": 1776930690697, "temp": 19.8, "bat": 3}, {"time": 1776931296081, "temp": 19.7, "bat": 3}, {"time": 1776931890783, "temp": 19.5, "bat": 3}, {"time": 1776932491735, "temp": 19.8, "bat": 3}, {"time": 1776933092789, "temp": 19.7, "bat": 3}, {"time": 1776933692706, "temp": 18.6, "bat": 3}, {"time": 1776934294709, "temp": 19.4, "bat": 3}, {"time": 1776934894820, "temp": 19.5, "bat": 3}, {"time": 1776935494811, "temp": 18.7, "bat": 3}, {"time": 1776936095828, "temp": 18.7, "bat": 3}, {"time": 1776936695734, "temp": 18.4, "bat": 3}, {"time": 1776937300870, "temp": 18.6, "bat": 3}, {"time": 1776937896478, "temp": 18.3, "bat": 3}, {"time": 1776938495825, "temp": 18.3, "bat": 3}, {"time": 1776939095831, "temp": 17.9, "bat": 3}, {"time": 1776939695835, "temp": 17.6, "bat": 3}, {"time": 1776940300943, "temp": 17.6, "bat": 3}, {"time": 1776940895817, "temp": 17.4, "bat": 3}, {"time": 1776941495829, "temp": 17.1, "bat": 3}, {"time": 1776942095907, "temp": 16.8, "bat": 3}, {"time": 1776942695903, "temp": 16.6, "bat": 3}, {"time": 1776943301179, "temp": 16.5, "bat": 3}, {"time": 1776943896944, "temp": 16.7, "bat": 3}, {"time": 1776944497037, "temp": 16.4, "bat": 3}, {"time": 1776945096946, "temp": 16.4, "bat": 3}, {"time": 1776945696946, "temp": 16.6, "bat": 3}, {"time": 1776946301987, "temp": 16.4, "bat": 3}, {"time": 1776946896946, "temp": 16.2, "bat": 3}, {"time": 1776947497016, "temp": 16.1, "bat": 3}, {"time": 1776948096942, "temp": 15.5, "bat": 3}, {"time": 1776948697665, "temp": 15.7, "bat": 3}, {"time": 1776949301900, "temp": 15.5, "bat": 3}, {"time": 1776949896950, "temp": 15.0, "bat": 3}, {"time": 1776950496935, "temp": 15.4, "bat": 3}, {"time": 1776951096864, "temp": 15.5, "bat": 3}, {"time": 1776951696944, "temp": 15.3, "bat": 3}, {"time": 1776952301988, "temp": 15.6, "bat": 3}, {"time": 1776952896939, "temp": 15.3, "bat": 3}, {"time": 1776953497021, "temp": 14.6, "bat": 3}, {"time": 1776954096872, "temp": 15.4, "bat": 3}, {"time": 1776954697658, "temp": 15.3, "bat": 3}, {"time": 1776955301908, "temp": 15.5, "bat": 3}, {"time": 1776955897011, "temp": 15.3, "bat": 3}, {"time": 1776956497902, "temp": 15.1, "bat": 3}, {"time": 1776957099679, "temp": 15.4, "bat": 3}, {"time": 1776957699025, "temp": 15.4, "bat": 3}, {"time": 1776958303981, "temp": 15.5, "bat": 3}, {"time": 1776958899357, "temp": 15.2, "bat": 3}, {"time": 1776959499281, "temp": 15.3, "bat": 3}, {"time": 1776960099027, "temp": 15.1, "bat": 3}, {"time": 1776960699027, "temp": 15.6, "bat": 3} ]}
